snorbyte/client.cpython-310-i386-linux-gnu.so
snorbyte/client.c
snorbyte/__init__.py
snorbyte-0.1.13.dist-info/WHEEL
snorbyte-0.1.13.dist-info/top_level.txt
snorbyte-0.1.13.dist-info/METADATA
snorbyte-0.1.13.dist-info/RECORD
