Metadata-Version: 2.4
Name: snorbyte
Version: 0.1.13
Summary: Snorbyte TTS client with streaming and playback
Home-page: https://snorbyte.com
Author: Snorbyte
Author-email: aakash@snorbyte.com
License: MIT
Project-URL: Source, https://github.com/snorbyte/snorbyte-python
Project-URL: Issues, https://github.com/snorbyte/snorbyte-python/issues
Classifier: Programming Language :: Python :: 3
Classifier: Programming Language :: Python :: 3 :: Only
Classifier: Programming Language :: Python :: 3.9
Classifier: Programming Language :: Python :: 3.10
Classifier: Programming Language :: Python :: 3.11
Classifier: Programming Language :: Python :: 3.12
Classifier: License :: OSI Approved :: MIT License
Classifier: Operating System :: Microsoft :: Windows
Classifier: Operating System :: MacOS :: MacOS X
Classifier: Operating System :: POSIX :: Linux
Classifier: Topic :: Multimedia :: Sound/Audio :: Players
Classifier: Topic :: Multimedia :: Sound/Audio :: Speech
Requires-Python: >=3.9
Requires-Dist: requests>=2.31
Requires-Dist: numpy>=1.26
Requires-Dist: sounddevice>=0.4.6
Requires-Dist: websocket-client>=1.8.0
